mdsanima_cli/__init__.py
mdsanima_cli/__main__.py
mdsanima_cli/_version.py
mdsanima_cli/parser.py
mdsanima_cli/commands/__init__.py
mdsanima_cli/commands/check.py
mdsanima_cli/commands/gifmaker.py
mdsanima_cli/commands/grid.py
mdsanima_cli/commands/jpg.py
mdsanima_cli/commands/logo.py
mdsanima_cli/commands/number.py
mdsanima_cli/commands/pixelart.py
mdsanima_cli/commands/png.py
mdsanima_cli/commands/resize.py
mdsanima_cli/commands/thumbnail.py
mdsanima_cli/commands/uuids.py
mdsanima_cli/commands/watermark.py
mdsanima_cli/commands/webp.py
mdsanima_cli/utils/__init__.py
mdsanima_cli/utils/ascii.py
mdsanima_cli/utils/exif.py
mdsanima_cli/utils/print.py
mdsanima_cli/utils/stats.py
mdsanima_cli/utils/timer.py
mdsanima_cli-0.3.0.dist-info/LICENSE
mdsanima_cli-0.3.0.dist-info/METADATA
mdsanima_cli-0.3.0.dist-info/WHEEL
mdsanima_cli-0.3.0.dist-info/entry_points.txt
mdsanima_cli-0.3.0.dist-info/top_level.txt
mdsanima_cli-0.3.0.dist-info/RECORD
