Metadata-Version: 2.1
Name: mdsanima-cli
Version: 0.3.0
Summary: Command-line tools for image processing, generating pixel art, adding logos to images, and much more.
Author-email: Marcin Różewski <marcinrozewski@gmail.com>
License: Apache License
Project-URL: homepage, https://github.com/mdsanima-lab/mdsanima-cli
Project-URL: documentation, https://github.com/mdsanima-lab/mdsanima-cli#readme
Project-URL: repository, https://github.com/mdsanima-lab/mdsanima-cli.git
Project-URL: changelog, https://github.com/mdsanima-lab/mdsanima-cli/blob/main/CHANGELOG.md
Keywords: bash,cli,command-line,console-app,console-application,exif metadata,exif,image-processing,images,logo,mdsanima command line,mdsanima command-line,mdsanima-cli,mdsanima-dev,mdsanima,meta information,pixel art,pixelart,python-library,python,python3,shell-script,shell,watermark,zsh
Classifier: Development Status :: 2 - Pre-Alpha
Classifier: Environment :: Console
Classifier: Environment :: Plugins
Classifier: Intended Audience :: Developers
Classifier: Intended Audience :: Education
Classifier: Intended Audience :: End Users/Desktop
Classifier: Intended Audience :: Information Technology
Classifier: Intended Audience :: Legal Industry
Classifier: Intended Audience :: Other Audience
Classifier: Intended Audience :: System Administrators
Classifier: License :: OSI Approved :: Apache Software License
Classifier: Natural Language :: English
Classifier: Natural Language :: Polish
Classifier: Operating System :: MacOS
Classifier: Operating System :: Microsoft :: Windows
Classifier: Operating System :: POSIX :: BSD
Classifier: Operating System :: POSIX :: Linux
Classifier: Operating System :: Unix
Classifier: Programming Language :: Python :: 3.10
Classifier: Programming Language :: Python :: 3.11
Classifier: Topic :: Desktop Environment
Classifier: Topic :: Documentation :: Sphinx
Classifier: Topic :: Education :: Testing
Classifier: Topic :: Multimedia
Classifier: Topic :: Multimedia :: Graphics
Classifier: Topic :: Multimedia :: Graphics :: Editors
Classifier: Topic :: Scientific/Engineering :: Image Processing
Classifier: Topic :: Scientific/Engineering :: Information Analysis
Classifier: Topic :: Software Development
Classifier: Topic :: Software Development :: Libraries :: Python Modules
Classifier: Topic :: System
Classifier: Topic :: System :: Console Fonts
Classifier: Topic :: System :: Filesystems
Classifier: Topic :: System :: Logging
Classifier: Topic :: System :: Operating System
Classifier: Topic :: System :: Shells
Classifier: Topic :: System :: System Shells
Classifier: Topic :: System :: Systems Administration
Classifier: Topic :: System :: Systems Administration :: Authentication/Directory
Classifier: Topic :: Terminals
Classifier: Topic :: Text Processing
Classifier: Topic :: Utilities
Classifier: Typing :: Typed
Requires-Python: >=3.10
License-File: LICENSE
Requires-Dist: mdsanima-dev ==0.1.1
Requires-Dist: piexif ==1.1.3
Requires-Dist: pillow ==10.0.1
Provides-Extra: dev
Requires-Dist: black ==23.9.1 ; extra == 'dev'
Requires-Dist: build ==1.0.3 ; extra == 'dev'
Requires-Dist: flake8 ==6.1.0 ; extra == 'dev'
Requires-Dist: isort ==5.12.0 ; extra == 'dev'
Requires-Dist: pylint ==3.0.1 ; extra == 'dev'
Requires-Dist: setuptools-scm ==8.0.4 ; extra == 'dev'
Requires-Dist: twine ==4.0.2 ; extra == 'dev'
Requires-Dist: virtualenv ==20.24.5 ; extra == 'dev'
